pyright_polite/__about__.py
pyright_polite/__init__.py
pyright_polite/cli.py
pyright_polite/main.py
pyright_polite/platform.py
pyright_polite/polite.py
pyright_polite/pyright.py
pyright_polite-1.0.5.dist-info/METADATA
pyright_polite-1.0.5.dist-info/WHEEL
pyright_polite-1.0.5.dist-info/entry_points.txt
pyright_polite-1.0.5.dist-info/licenses/LICENSE
pyright_polite-1.0.5.dist-info/RECORD
