Metadata-Version: 2.1
Name: pyright-polite
Version: 1.0.5
Summary: An intelligent cross-platform wrapper for pyright that makes it less noisy.
Project-URL: Homepage, https://github.com/jamielinux/pyright-polite
Project-URL: Issues, https://github.com/jamielinux/pyright-polite/issues
Project-URL: Source, https://github.com/jamielinux/pyright-polite
Author-email: Jamie Nguyen <j@jamielinux.com>
License-Expression: MIT
License-File: LICENSE
Keywords: pyright,quiet
Classifier: Development Status :: 5 - Production/Stable
Classifier: Environment :: Console
Classifier: Intended Audience :: Developers
Classifier: License :: OSI Approved :: MIT License
Classifier: Programming Language :: Python
Classifier: Programming Language :: Python :: 3.7
Classifier: Programming Language :: Python :: 3.8
Classifier: Programming Language :: Python :: 3.9
Classifier: Programming Language :: Python :: 3.10
Classifier: Programming Language :: Python :: 3.11
Classifier: Programming Language :: Python :: Implementation :: CPython
Classifier: Programming Language :: Python :: Implementation :: PyPy
Requires-Python: >=3.7
Requires-Dist: colorama~=0.4.6
